passagemath_standard_no_symbolics-10.6.43.data/scripts/sage-grep
passagemath_standard_no_symbolics-10.6.43.data/scripts/sage-list-packages
passagemath_standard_no_symbolics-10.6.43.data/scripts/sage-grepdoc
passagemath_standard_no_symbolics-10.6.43.dist-info/RECORD
passagemath_standard_no_symbolics-10.6.43.dist-info/WHEEL
passagemath_standard_no_symbolics-10.6.43.dist-info/top_level.txt
passagemath_standard_no_symbolics-10.6.43.dist-info/METADATA
passagemath_standard_no_symbolics/__init__.py
sage/all_cmdline.py
sage/all.py
sage/misc/lazy_attribute.pyi
sage/misc/all.py
sage/databases/cubic_hecke_db.py
sage/databases/all.py
sage/dynamics/surface_dynamics_deprecation.py
sage/dynamics/all.py
sage/ext_data/nodoctest
sage/ext_data/kenzo/S4.txt
sage/ext_data/kenzo/CP4.txt
sage/ext_data/kenzo/CP2.txt
sage/ext_data/kenzo/CP3.txt
sage/ext_data/kenzo/README.txt
sage/ext_data/mwrank/PRIMES
sage/ext_data/notebook-ipython/logo-64x64.png
sage/ext_data/notebook-ipython/kernel.json.in
sage/ext_data/notebook-ipython/logo.svg
sage/ext_data/nbconvert/rst_sage.tpl
sage/ext_data/nbconvert/postprocess.py
sage/ext_data/valgrind/sage-additional.supp
sage/ext_data/valgrind/valgrind-python.supp
sage/ext_data/valgrind/pyalloc.supp
sage/ext_data/valgrind/sage.supp
sage/interacts/library.py
sage/interacts/library_cython.cpython-314t-darwin.so
sage/interacts/algebra.py
sage/interacts/all.py
sage/interacts/calculus.py
sage/interacts/fractals.py
sage/interacts/geometry.py
sage/interacts/statistics.py
sage/logic/logicparser.py
sage/logic/all.py
sage/logic/propcalc.py
sage/logic/logic.py
sage/logic/booleval.py
sage/logic/boolformula.py
sage/logic/logictable.py
sage/groups/matrix_gps/pickling_overrides.py
sage/cli/notebook_cmd.py
sage/cli/options.py
sage/cli/eval_cmd.py
sage/cli/__init__.py
sage/cli/eval_cmd_test.py
sage/cli/version_cmd.py
sage/cli/__main__.py
sage/cli/notebook_cmd_test.py
sage/cli/interactive_shell_cmd.py
sage/cli/run_file_cmd.py
sage/libs/all.py
sage/libs/cremona/__init__.py
sage/libs/mwrank/__init__.py
sage/rings/commutative_algebra.py
sage/rings/all.py
sage/rings/numbers_abc.py
sage/rings/polynomial/convolution.py
sage/rings/polynomial/all.py
