Metadata-Version: 2.4
Name: passagemath-standard-no-symbolics
Version: 10.6.43
Summary: passagemath: Sage library without the symbolics subsystem
Author-email: The Sage Developers <sage-support@googlegroups.com>
Maintainer: Matthias Köppe, passagemath contributors
License-Expression: GPL-2.0-or-later
Project-URL: release notes, https://github.com/passagemath/passagemath/releases
Project-URL: repo (upstream), https://github.com/sagemath/sage
Project-URL: repo, https://github.com/passagemath/passagemath
Project-URL: documentation, https://passagemath.org/docs/latest
Project-URL: homepage (upstream), https://www.sagemath.org
Project-URL: discourse, https://passagemath.discourse.group
Project-URL: tracker (upstream), https://github.com/sagemath/sage/issues
Project-URL: tracker, https://github.com/passagemath/passagemath/issues
Classifier: Development Status :: 6 - Mature
Classifier: Intended Audience :: Education
Classifier: Intended Audience :: Science/Research
Classifier: Operating System :: POSIX
Classifier: Operating System :: POSIX :: Linux
Classifier: Operating System :: MacOS :: MacOS X
Classifier: Programming Language :: Python :: 3 :: Only
Classifier: Programming Language :: Python :: 3.10
Classifier: Programming Language :: Python :: 3.11
Classifier: Programming Language :: Python :: 3.12
Classifier: Programming Language :: Python :: 3.13
Classifier: Programming Language :: Python :: 3.14
Classifier: Programming Language :: Python :: Implementation :: CPython
Classifier: Topic :: Scientific/Engineering :: Mathematics
Requires-Python: <3.15,>=3.10
Requires-Dist: six>=1.15.0
Requires-Dist: passagemath-brial~=10.6.43.0
Requires-Dist: passagemath-categories~=10.6.43.0
Requires-Dist: passagemath-cddlib~=10.6.43.0
Requires-Dist: passagemath-combinat~=10.6.43.0
Requires-Dist: passagemath-eclib~=10.6.43.0
Requires-Dist: passagemath-environment~=10.6.43.0
Requires-Dist: passagemath-flint~=10.6.43.0
Requires-Dist: passagemath-gap~=10.6.43.0
Requires-Dist: passagemath-gap-pkg-transgrp-data~=10.6.43.0
Requires-Dist: passagemath-gap-pkg-ctbllib-data~=10.6.43.0
Requires-Dist: passagemath-gap-pkg-tomlib-data~=10.6.43.0
Requires-Dist: passagemath-gap-pkg-irredsol-data~=10.6.43.0
Requires-Dist: passagemath-glpk~=10.6.43.0
Requires-Dist: passagemath-graphs~=10.6.43.0
Requires-Dist: passagemath-groups~=10.6.43.0
Requires-Dist: passagemath-homfly~=10.6.43.0
Requires-Dist: passagemath-lcalc~=10.6.43.0
Requires-Dist: passagemath-libbraiding~=10.6.43.0
Requires-Dist: passagemath-libecm~=10.6.43.0
Requires-Dist: passagemath-linbox~=10.6.43.0
Requires-Dist: passagemath-modules~=10.6.43.0
Requires-Dist: passagemath-nauty~=10.6.43.0
Requires-Dist: passagemath-ntl~=10.6.43.0
Requires-Dist: passagemath-objects~=10.6.43.0
Requires-Dist: passagemath-palp~=10.6.43.0
Requires-Dist: passagemath-pari~=10.6.43.0
Requires-Dist: passagemath-pari-galdata~=10.6.43.0
Requires-Dist: passagemath-pari-seadata-small~=10.6.43.0
Requires-Dist: passagemath-planarity~=10.6.43.0
Requires-Dist: passagemath-plot~=10.6.43.0
Requires-Dist: passagemath-polyhedra~=10.6.43.0
Requires-Dist: passagemath-repl~=10.6.43.0
Requires-Dist: passagemath-schemes~=10.6.43.0
Requires-Dist: passagemath-singular~=10.6.43.0
Requires-Dist: passagemath-tachyon~=10.6.43.0
Requires-Dist: cysignals!=1.12.4; sys_platform == "win32"
Requires-Dist: cysignals!=1.12.0,>=1.11.2
Requires-Dist: cython<3.3.0,>=3.0.8
Requires-Dist: cython<3.3.0,>=3.0.8
Requires-Dist: gmpy2~=2.1.b999
Requires-Dist: jupyter-core
Requires-Dist: lrcalc
Requires-Dist: memory_allocator
Requires-Dist: numpy>=1.19
Requires-Dist: numpy>=1.22.4
Requires-Dist: pkgconfig
Requires-Dist: passagemath-ppl
Requires-Dist: passagemath-primesieve-primecount
Requires-Dist: requests>=2.13.0
Requires-Dist: ipython>=7.13.0
Requires-Dist: pexpect>=4.8.0
Requires-Dist: sphinx<9,>=5.2
Requires-Dist: networkx>=2.4
Requires-Dist: scipy>=1.5
Requires-Dist: matplotlib>=3.5.1
Requires-Dist: pillow>=7.2.0
Requires-Dist: ipykernel>=5.2.1
Requires-Dist: jupyter-client
Requires-Dist: ipywidgets>=7.5.1
Requires-Dist: fpylll>=0.5.9
Requires-Dist: ptyprocess>0.5
Provides-Extra: test
